presets/base.toml
presets/python.toml
styles/bandit.toml
styles/black.toml
styles/editorconfig.toml
styles/isort.toml
styles/nitpick.toml
styles/poetry.toml
styles/pylint.toml
styles/python-base.toml
vmeurisse_nitpick_styles.py
vmeurisse_nitpick_styles-0.1.2.dist-info/WHEEL
vmeurisse_nitpick_styles-0.1.2.dist-info/METADATA
vmeurisse_nitpick_styles-0.1.2.dist-info/RECORD
